{
  "battle_id": "battle-gen9randombattle-331",
  "format": "gen9randombattle",
  "started_at": "2025-05-16T12:43:13.883985",
  "our_team": {
    "p1: Drednaw": {
      "species": "drednaw",
      "types": [
        "WATER (pokemon type) object",
        "ROCK (pokemon type) object"
      ],
      "level": 81,
      "hp": 1.0,
      "status": null,
      "moves": {
        "shellsmash": {
          "id": "shellsmash",
          "type": "NORMAL (pokemon type) object",
          "base_power": 0,
          "category": 